keyvox/_article.py
keyvox/_author.py
keyvox/_tag.py
keyvox/keyvox.py
keyvox-0.1.4.dist-info/METADATA
keyvox-0.1.4.dist-info/WHEEL
keyvox-0.1.4.dist-info/RECORD
