Metadata-Version: 2.1
Name: keyvox
Version: 0.1.4
Summary: keyvox.dev official package for python
Author: keyvox-dev
Author-email: 157120239+keyvox-dev@users.noreply.github.com
Requires-Python: >=3.12,<4.0
Classifier: Programming Language :: Python :: 3
Classifier: Programming Language :: Python :: 3.12
Requires-Dist: pytest (>=7.4.4,<8.0.0)
Requires-Dist: requests (>=2.31.0,<3.0.0)
